sophgotools/__init__.py
sophgotools/cmdline.so
sophgotools/execute.so
sophgotools/hub_file_utils.so
sophgotools/logger.so
sophgotools/user.so
sophgotools/utils.so
sophgotools-1.0.2.dist-info/METADATA
sophgotools-1.0.2.dist-info/WHEEL
sophgotools-1.0.2.dist-info/entry_points.txt
sophgotools-1.0.2.dist-info/top_level.txt
sophgotools-1.0.2.dist-info/RECORD
