Metadata-Version: 2.1
Name: sophgotools
Version: 1.0.2
Summary: cogleapai
Home-page: UNKNOWN
Author: UNKNOWN
Author-email: UNKNOWN
License: Apache License 2.0
Platform: UNKNOWN
Requires-Dist: modelscope (==1.20.1)
Requires-Dist: onnx (==1.12.0)
Requires-Dist: openpyxl (==3.1.5)
Requires-Dist: psutil (==6.1.1)
